"discord_ext_help/__init__,py"
discord_ext_help/help.py
discord_ext_help/legacy/__init__.py
discord_ext_help/legacy/config.py
discord_ext_help/legacy/extension.py
discord_ext_help-1.0.1.dist-info/LICENSE
discord_ext_help-1.0.1.dist-info/METADATA
discord_ext_help-1.0.1.dist-info/WHEEL
discord_ext_help-1.0.1.dist-info/RECORD
