Metadata-Version: 2.1
Name: discord-ext-help
Version: 1.0.1
Summary: A discord.py extension that automatically generates interaction help commands.
Home-page: https://github.com/sonyakun/discord-ext-help
Author: sonyakun
Author-email: owner@sonyakun.com
Requires-Python: >=3.8,<4.0
Classifier: Programming Language :: Python :: 3
Classifier: Programming Language :: Python :: 3.8
Classifier: Programming Language :: Python :: 3.9
Classifier: Programming Language :: Python :: 3.10
Classifier: Programming Language :: Python :: 3.11
Classifier: Programming Language :: Python :: 3.12
Requires-Dist: discord-py (>=2.0.0,<3.0.0)
Requires-Dist: reactionmenu (>=3.1.5,<4.0.0)
Project-URL: Repository, https://github.com/sonyakun/discord-ext-help
